{"skeleton":{"hash":"Pvr27OY9rsm986dlbLReu2dGrQg","spine":"2.1.27","width":434.45,"height":514.43,"images":"./robot_spine/"},"bones":[{"name":"root"},{"name":"body","parent":"root","length":215.99,"x":-11.07,"y":121.55,"rotation":91.8},{"name":"head","parent":"body","length":102.79,"x":220.29,"y":0.41,"rotation":0.45},{"name":"l_leg","parent":"body","length":93.72,"x":5.69,"y":-34.02,"rotation":-176.08},{"name":"l_shoulder","parent":"body","length":65.47,"x":177.96,"y":-34.55,"rotation":-83.26},{"name":"r_leg","parent":"body","length":97.66,"x":7.23,"y":34.22,"rotation":-176.39},{"name":"r_shoulder","parent":"body","length":79.94,"x":183.82,"y":34.17,"rotation":85.31},{"name":"l_arm","parent":"l_shoulder","length":52.55,"x":65.47,"y":-2.54,"rotation":1.89},{"name":"l_foot","parent":"l_leg","length":29.43,"x":97.4,"y":-0.15,"rotation":75.43},{"name":"r_arm","parent":"r_shoulder","length":53.1,"x":80.81,"y":-0.38,"rotation":2.96},{"name":"r_foot","parent":"r_leg","length":30.23,"x":102.62,"y":0.77,"rotation":80.17},{"name":"smile","parent":"head","x":49.28,"y":-10.91},{"name":"l_hand","parent":"l_arm","length":41.97,"x":52.55,"y":0.21,"rotation":2.25},{"name":"r_hand","parent":"r_arm","length":39.11,"x":53.1,"y":-0.05,"rotation":0.13}],"slots":[{"name":"l_leg","bone":"l_leg","attachment":"l_leg"},{"name":"l_foot","bone":"l_foot","attachment":"l_foot"},{"name":"l_shoulder","bone":"l_shoulder","attachment":"l_shoulder"},{"name":"l_arm","bone":"l_arm","attachment":"l_arm"},{"name":"l_hand","bone":"l_hand","attachment":"l_hand"},{"name":"body","bone":"body","attachment":"body"},{"name":"r_leg","bone":"r_leg","attachment":"r_leg"},{"name":"r_foot","bone":"r_foot","attachment":"r_foot"},{"name":"head","bone":"head","attachment":"head"},{"name":"smile","bone":"smile","attachment":"smile"},{"name":"r_shoulder","bone":"r_shoulder","attachment":"r_shoulder"},{"name":"r_arm","bone":"r_arm","attachment":"r_arm"},{"name":"r_hand","bone":"r_hand","attachment":"r_hand"}],"skins":{"default":{"body":{"body":{"x":107.98,"y":-9.81,"rotation":-91.8,"width":160,"height":239}},"head":{"head":{"x":81.27,"y":3.91,"rotation":-92.25,"width":196,"height":182}},"l_arm":{"l_arm":{"x":26.78,"y":0.01,"rotation":57.67,"width":43,"height":58}},"l_foot":{"l_foot":{"x":6.33,"y":-9.45,"rotation":10.48,"width":56,"height":39}},"l_hand":{"l_hand":{"x":27.77,"y":0.93,"rotation":55.41,"width":47,"height":47}},"l_leg":{"l_leg":{"x":46.23,"y":-2.81,"rotation":85.92,"width":30,"height":100}},"l_shoulder":{"l_shoulder":{"x":33.26,"y":0.5,"rotation":62.17,"width":45,"height":74}},"r_arm":{"r_arm":{"x":24.96,"y":-2.16,"rotation":61.6,"width":44,"height":59}},"r_foot":{"r_foot":{"x":9.82,"y":-4.48,"rotation":4.41,"width":61,"height":42}},"r_hand":{"r_hand":{"x":24.08,"y":-0.68,"rotation":53.54,"width":45,"height":50}},"r_leg":{"r_leg":{"x":40.74,"y":1.07,"rotation":84.59,"width":32,"height":106}},"r_shoulder":{"r_shoulder":{"x":41.97,"y":-0.84,"rotation":126.69,"width":62,"height":75}},"smile":{"smile":{"x":-4.54,"y":-6.55,"rotation":-92.25,"width":77,"height":62}}}},"animations":{"idle":{"bones":{"root":{"rotate":[{"time":0,"angle":0,"curve":"stepped"},{"time":1,"angle":0,"curve":"stepped"},{"time":1.6666,"angle":0,"curve":"stepped"},{"time":2,"angle":0,"curve":"stepped"},{"time":2.6666,"angle":0,"curve":"stepped"},{"time":3.3333,"angle":0}],"translate":[{"time":0,"x":0,"y":0,"curve":"stepped"},{"time":1,"x":0,"y":0,"curve":"stepped"},{"time":1.6666,"x":0,"y":0,"curve":"stepped"},{"time":2,"x":0,"y":0,"curve":"stepped"},{"time":2.6666,"x":0,"y":0,"curve":"stepped"},{"time":3.3333,"x":0,"y":0}]},"body":{"rotate":[{"time":0,"angle":0,"curve":"stepped"},{"time":1,"angle":0},{"time":1.6666,"angle":2.67},{"time":2,"angle":0},{"time":2.6666,"angle":-4.97},{"time":3.3333,"angle":0}],"translate":[{"time":0,"x":0,"y":0,"curve":"stepped"},{"time":1,"x":0,"y":0},{"time":1.6666,"x":7.19,"y":7.71},{"time":2,"x":0,"y":0},{"time":2.6666,"x":-6.6,"y":-0.82},{"time":3.3333,"x":0,"y":0}]},"head":{"rotate":[{"time":0,"angle":0,"curve":"stepped"},{"time":1,"angle":0,"curve":"stepped"},{"time":1.6666,"angle":0,"curve":"stepped"},{"time":2,"angle":0,"curve":"stepped"},{"time":2.6666,"angle":0,"curve":"stepped"},{"time":3.3333,"angle":0}],"translate":[{"time":0,"x":0,"y":0,"curve":"stepped"},{"time":1,"x":0,"y":0,"curve":"stepped"},{"time":1.6666,"x":0,"y":0,"curve":"stepped"},{"time":2,"x":0,"y":0,"curve":"stepped"},{"time":2.6666,"x":0,"y":0,"curve":"stepped"},{"time":3.3333,"x":0,"y":0}]},"l_leg":{"rotate":[{"time":0,"angle":0,"curve":"stepped"},{"time":1,"angle":0},{"time":1.6666,"angle":-3.77},{"time":2,"angle":0},{"time":2.6666,"angle":9.12},{"time":3.3333,"angle":0}],"translate":[{"time":0,"x":0,"y":0,"curve":"stepped"},{"time":1,"x":0,"y":0},{"time":1.6666,"x":-5.32,"y":1.19},{"time":2,"x":0,"y":0},{"time":2.6666,"x":2.74,"y":0.23},{"time":3.3333,"x":0,"y":0}]},"l_shoulder":{"rotate":[{"time":0,"angle":-81.88,"curve":"stepped"},{"time":1,"angle":-81.88,"curve":"stepped"},{"time":1.6666,"angle":-81.88,"curve":"stepped"},{"time":2,"angle":-81.88,"curve":"stepped"},{"time":2.6666,"angle":-81.88,"curve":"stepped"},{"time":3.3333,"angle":-81.88}],"translate":[{"time":0,"x":0,"y":0,"curve":"stepped"},{"time":1,"x":0,"y":0,"curve":"stepped"},{"time":1.6666,"x":0,"y":0,"curve":"stepped"},{"time":2,"x":0,"y":0,"curve":"stepped"},{"time":2.6666,"x":0,"y":0,"curve":"stepped"},{"time":3.3333,"x":0,"y":0}]},"r_leg":{"rotate":[{"time":0,"angle":0,"curve":"stepped"},{"time":1,"angle":0},{"time":1.6666,"angle":352.92},{"time":2,"angle":0},{"time":2.6666,"angle":5.57},{"time":3.3333,"angle":0}],"translate":[{"time":0,"x":0,"y":0,"curve":"stepped"},{"time":1,"x":0,"y":0,"curve":"stepped"},{"time":1.6666,"x":0,"y":0,"curve":"stepped"},{"time":2,"x":0,"y":0},{"time":2.6666,"x":-1.5,"y":-4.21},{"time":3.3333,"x":0,"y":0}]},"r_shoulder":{"rotate":[{"time":0,"angle":74.87,"curve":"stepped"},{"time":1,"angle":74.87,"curve":"stepped"},{"time":1.6666,"angle":74.87,"curve":"stepped"},{"time":2,"angle":74.87,"curve":"stepped"},{"time":2.6666,"angle":74.87,"curve":"stepped"},{"time":3.3333,"angle":74.87}],"translate":[{"time":0,"x":0,"y":0,"curve":"stepped"},{"time":1,"x":0,"y":0,"curve":"stepped"},{"time":1.6666,"x":0,"y":0,"curve":"stepped"},{"time":2,"x":0,"y":0,"curve":"stepped"},{"time":2.6666,"x":0,"y":0,"curve":"stepped"},{"time":3.3333,"x":0,"y":0}]},"l_arm":{"rotate":[{"time":0,"angle":17.45,"curve":"stepped"},{"time":1,"angle":17.45,"curve":"stepped"},{"time":1.6666,"angle":17.45,"curve":"stepped"},{"time":2,"angle":17.45,"curve":"stepped"},{"time":2.6666,"angle":17.45,"curve":"stepped"},{"time":3.3333,"angle":17.45}],"translate":[{"time":0,"x":0,"y":0,"curve":"stepped"},{"time":1,"x":0,"y":0,"curve":"stepped"},{"time":1.6666,"x":0,"y":0,"curve":"stepped"},{"time":2,"x":0,"y":0,"curve":"stepped"},{"time":2.6666,"x":0,"y":0,"curve":"stepped"},{"time":3.3333,"x":0,"y":0}]},"l_foot":{"rotate":[{"time":0,"angle":0,"curve":"stepped"},{"time":1,"angle":0},{"time":1.6666,"angle":-18.44},{"time":2,"angle":0},{"time":2.6666,"angle":-4.76},{"time":3.3333,"angle":0}],"translate":[{"time":0,"x":0,"y":0,"curve":"stepped"},{"time":1,"x":0,"y":0,"curve":"stepped"},{"time":1.6666,"x":0,"y":0,"curve":"stepped"},{"time":2,"x":0,"y":0,"curve":"stepped"},{"time":2.6666,"x":0,"y":0,"curve":"stepped"},{"time":3.3333,"x":0,"y":0}]},"r_arm":{"rotate":[{"time":0,"angle":27.46,"curve":"stepped"},{"time":1,"angle":27.46,"curve":"stepped"},{"time":1.6666,"angle":27.46,"curve":"stepped"},{"time":2,"angle":27.46,"curve":"stepped"},{"time":2.6666,"angle":27.46,"curve":"stepped"},{"time":3.3333,"angle":27.46}],"translate":[{"time":0,"x":0,"y":0,"curve":"stepped"},{"time":1,"x":0,"y":0,"curve":"stepped"},{"time":1.6666,"x":0,"y":0,"curve":"stepped"},{"time":2,"x":0,"y":0,"curve":"stepped"},{"time":2.6666,"x":0,"y":0,"curve":"stepped"},{"time":3.3333,"x":0,"y":0}]},"r_foot":{"rotate":[{"time":0,"angle":0,"curve":"stepped"},{"time":1,"angle":0},{"time":1.6666,"angle":-10.39},{"time":2,"angle":0},{"time":2.6666,"angle":-1.17},{"time":3.3333,"angle":0}],"translate":[{"time":0,"x":0,"y":0,"curve":"stepped"},{"time":1,"x":0,"y":0,"curve":"stepped"},{"time":1.6666,"x":0,"y":0,"curve":"stepped"},{"time":2,"x":0,"y":0,"curve":"stepped"},{"time":2.6666,"x":0,"y":0,"curve":"stepped"},{"time":3.3333,"x":0,"y":0}]},"smile":{"rotate":[{"time":0,"angle":0,"curve":"stepped"},{"time":1,"angle":0,"curve":"stepped"},{"time":1.6666,"angle":0,"curve":"stepped"},{"time":2,"angle":0,"curve":"stepped"},{"time":2.6666,"angle":0,"curve":"stepped"},{"time":3.3333,"angle":0}],"translate":[{"time":0,"x":0,"y":0,"curve":"stepped"},{"time":1,"x":0,"y":0,"curve":"stepped"},{"time":1.6666,"x":0,"y":0,"curve":"stepped"},{"time":2,"x":0,"y":0,"curve":"stepped"},{"time":2.6666,"x":0,"y":0,"curve":"stepped"},{"time":3.3333,"x":0,"y":0}]},"l_hand":{"rotate":[{"time":0,"angle":0,"curve":"stepped"},{"time":1,"angle":0,"curve":"stepped"},{"time":1.6666,"angle":0,"curve":"stepped"},{"time":2,"angle":0,"curve":"stepped"},{"time":2.6666,"angle":0,"curve":"stepped"},{"time":3.3333,"angle":0}],"translate":[{"time":0,"x":0,"y":0,"curve":"stepped"},{"time":1,"x":0,"y":0,"curve":"stepped"},{"time":1.6666,"x":0,"y":0,"curve":"stepped"},{"time":2,"x":0,"y":0,"curve":"stepped"},{"time":2.6666,"x":0,"y":0,"curve":"stepped"},{"time":3.3333,"x":0,"y":0}]},"r_hand":{"rotate":[{"time":0,"angle":0,"curve":"stepped"},{"time":1,"angle":0,"curve":"stepped"},{"time":1.6666,"angle":0,"curve":"stepped"},{"time":2,"angle":0,"curve":"stepped"},{"time":2.6666,"angle":0,"curve":"stepped"},{"time":3.3333,"angle":0}],"translate":[{"time":0,"x":0,"y":0,"curve":"stepped"},{"time":1,"x":0,"y":0,"curve":"stepped"},{"time":1.6666,"x":0,"y":0,"curve":"stepped"},{"time":2,"x":0,"y":0,"curve":"stepped"},{"time":2.6666,"x":0,"y":0,"curve":"stepped"},{"time":3.3333,"x":0,"y":0}]}}},"idle2":{"bones":{"root":{"rotate":[{"time":0,"angle":0,"curve":"stepped"},{"time":1.3333,"angle":0,"curve":"stepped"},{"time":2.6666,"angle":0}],"translate":[{"time":0,"x":0,"y":0,"curve":"stepped"},{"time":1.3333,"x":0,"y":0,"curve":"stepped"},{"time":2.6666,"x":0,"y":0}]},"body":{"rotate":[{"time":0,"angle":0},{"time":1.3333,"angle":6.78},{"time":2.6666,"angle":0}],"translate":[{"time":0,"x":1.9,"y":-111.26,"curve":"stepped"},{"time":1.3333,"x":1.9,"y":-111.26,"curve":"stepped"},{"time":2.6666,"x":1.9,"y":-111.26}]},"head":{"rotate":[{"time":0,"angle":0,"curve":"stepped"},{"time":1.3333,"angle":0,"curve":"stepped"},{"time":2.6666,"angle":0}],"translate":[{"time":0,"x":0,"y":0,"curve":"stepped"},{"time":1.3333,"x":0,"y":0,"curve":"stepped"},{"time":2.6666,"x":0,"y":0}]},"l_leg":{"rotate":[{"time":0,"angle":87.56},{"time":1.3333,"angle":79.54},{"time":2.6666,"angle":87.56}],"translate":[{"time":0,"x":0,"y":0,"curve":"stepped"},{"time":1.3333,"x":0,"y":0,"curve":"stepped"},{"time":2.6666,"x":0,"y":0}]},"l_shoulder":{"rotate":[{"time":0,"angle":53.15,"curve":"stepped"},{"time":1.3333,"angle":53.15,"curve":"stepped"},{"time":2.6666,"angle":53.15}],"translate":[{"time":0,"x":4.98,"y":-22.99,"curve":"stepped"},{"time":1.3333,"x":4.98,"y":-22.99,"curve":"stepped"},{"time":2.6666,"x":4.98,"y":-22.99}]},"r_leg":{"rotate":[{"time":0,"angle":85.83},{"time":1.3333,"angle":80.49},{"time":2.6666,"angle":85.83}],"translate":[{"time":0,"x":0,"y":0,"curve":"stepped"},{"time":1.3333,"x":0,"y":0,"curve":"stepped"},{"time":2.6666,"x":0,"y":0}]},"r_shoulder":{"rotate":[{"time":0,"angle":-30.9,"curve":"stepped"},{"time":1.3333,"angle":-30.9,"curve":"stepped"},{"time":2.6666,"angle":-30.9}],"translate":[{"time":0,"x":0,"y":0,"curve":"stepped"},{"time":1.3333,"x":0,"y":0,"curve":"stepped"},{"time":2.6666,"x":0,"y":0}]},"l_arm":{"rotate":[{"time":0,"angle":45.51,"curve":"stepped"},{"time":1.3333,"angle":45.51,"curve":"stepped"},{"time":2.6666,"angle":45.51}],"translate":[{"time":0,"x":0,"y":0,"curve":"stepped"},{"time":1.3333,"x":0,"y":0,"curve":"stepped"},{"time":2.6666,"x":0,"y":0}]},"l_foot":{"rotate":[{"time":0,"angle":0,"curve":"stepped"},{"time":1.3333,"angle":0,"curve":"stepped"},{"time":2.6666,"angle":0}],"translate":[{"time":0,"x":0,"y":0,"curve":"stepped"},{"time":1.3333,"x":0,"y":0,"curve":"stepped"},{"time":2.6666,"x":0,"y":0}]},"r_arm":{"rotate":[{"time":0,"angle":-38.88,"curve":"stepped"},{"time":1.3333,"angle":-38.88,"curve":"stepped"},{"time":2.6666,"angle":-38.88}],"translate":[{"time":0,"x":0,"y":0,"curve":"stepped"},{"time":1.3333,"x":0,"y":0,"curve":"stepped"},{"time":2.6666,"x":0,"y":0}]},"r_foot":{"rotate":[{"time":0,"angle":0,"curve":"stepped"},{"time":1.3333,"angle":0,"curve":"stepped"},{"time":2.6666,"angle":0}],"translate":[{"time":0,"x":0,"y":0,"curve":"stepped"},{"time":1.3333,"x":0,"y":0,"curve":"stepped"},{"time":2.6666,"x":0,"y":0}]},"smile":{"rotate":[{"time":0,"angle":0,"curve":"stepped"},{"time":1.3333,"angle":0,"curve":"stepped"},{"time":2.6666,"angle":0}],"translate":[{"time":0,"x":0,"y":0,"curve":"stepped"},{"time":1.3333,"x":0,"y":0,"curve":"stepped"},{"time":2.6666,"x":0,"y":0}]},"l_hand":{"rotate":[{"time":0,"angle":34.49,"curve":"stepped"},{"time":1.3333,"angle":34.49,"curve":"stepped"},{"time":2.6666,"angle":34.49}],"translate":[{"time":0,"x":0,"y":0,"curve":"stepped"},{"time":1.3333,"x":0,"y":0,"curve":"stepped"},{"time":2.6666,"x":0,"y":0}]},"r_hand":{"rotate":[{"time":0,"angle":-29.32,"curve":"stepped"},{"time":1.3333,"angle":-29.32,"curve":"stepped"},{"time":2.6666,"angle":-29.32}],"translate":[{"time":0,"x":0,"y":0,"curve":"stepped"},{"time":1.3333,"x":0,"y":0,"curve":"stepped"},{"time":2.6666,"x":0,"y":0}]}}},"idle3":{"bones":{"root":{"rotate":[{"time":0,"angle":0,"curve":"stepped"},{"time":1.3333,"angle":0,"curve":"stepped"},{"time":2.6666,"angle":0}],"translate":[{"time":0,"x":0,"y":0,"curve":"stepped"},{"time":1.3333,"x":0,"y":0,"curve":"stepped"},{"time":2.6666,"x":0,"y":0}]},"body":{"rotate":[{"time":0,"angle":-271.67,"curve":"stepped"},{"time":1.3333,"angle":-271.67,"curve":"stepped"},{"time":2.6666,"angle":-271.67}],"translate":[{"time":0,"x":13.15,"y":-46.03,"curve":"stepped"},{"time":1.3333,"x":13.15,"y":-46.03,"curve":"stepped"},{"time":2.6666,"x":13.15,"y":-46.03}]},"head":{"rotate":[{"time":0,"angle":-36.75,"curve":"stepped"},{"time":1.3333,"angle":-36.75,"curve":"stepped"},{"time":2.6666,"angle":-36.75}],"translate":[{"time":0,"x":0,"y":0,"curve":"stepped"},{"time":1.3333,"x":0,"y":0,"curve":"stepped"},{"time":2.6666,"x":0,"y":0}]},"l_leg":{"rotate":[{"time":0,"angle":0},{"time":1.3333,"angle":129.9},{"time":2.6666,"angle":0}],"translate":[{"time":0,"x":0,"y":0,"curve":"stepped"},{"time":1.3333,"x":0,"y":0,"curve":"stepped"},{"time":2.6666,"x":0,"y":0}]},"l_shoulder":{"rotate":[{"time":0,"angle":-96.24,"curve":"stepped"},{"time":1.3333,"angle":-96.24,"curve":"stepped"},{"time":2.6666,"angle":-96.24}],"translate":[{"time":0,"x":0,"y":0,"curve":"stepped"},{"time":1.3333,"x":0,"y":0,"curve":"stepped"},{"time":2.6666,"x":0,"y":0}]},"r_leg":{"rotate":[{"time":0,"angle":346.57,"curve":"stepped"},{"time":1.3333,"angle":346.57,"curve":"stepped"},{"time":2.6666,"angle":346.57}],"translate":[{"time":0,"x":0,"y":0,"curve":"stepped"},{"time":1.3333,"x":0,"y":0,"curve":"stepped"},{"time":2.6666,"x":0,"y":0}]},"r_shoulder":{"rotate":[{"time":0,"angle":-63.31,"curve":"stepped"},{"time":1.3333,"angle":-63.31,"curve":"stepped"},{"time":2.6666,"angle":-63.31}],"translate":[{"time":0,"x":0,"y":0,"curve":"stepped"},{"time":1.3333,"x":0,"y":0,"curve":"stepped"},{"time":2.6666,"x":0,"y":0}]},"l_arm":{"rotate":[{"time":0,"angle":0,"curve":"stepped"},{"time":1.3333,"angle":0,"curve":"stepped"},{"time":2.6666,"angle":0}],"translate":[{"time":0,"x":0,"y":0,"curve":"stepped"},{"time":1.3333,"x":0,"y":0,"curve":"stepped"},{"time":2.6666,"x":0,"y":0}]},"l_foot":{"rotate":[{"time":0,"angle":0,"curve":"stepped"},{"time":1.3333,"angle":0,"curve":"stepped"},{"time":2.6666,"angle":0}],"translate":[{"time":0,"x":0,"y":0,"curve":"stepped"},{"time":1.3333,"x":0,"y":0,"curve":"stepped"},{"time":2.6666,"x":0,"y":0}]},"r_arm":{"rotate":[{"time":0,"angle":-34.09,"curve":"stepped"},{"time":1.3333,"angle":-34.09,"curve":"stepped"},{"time":2.6666,"angle":-34.09}],"translate":[{"time":0,"x":0,"y":0,"curve":"stepped"},{"time":1.3333,"x":0,"y":0,"curve":"stepped"},{"time":2.6666,"x":0,"y":0}]},"r_foot":{"rotate":[{"time":0,"angle":0,"curve":"stepped"},{"time":1.3333,"angle":0,"curve":"stepped"},{"time":2.6666,"angle":0}],"translate":[{"time":0,"x":0,"y":0,"curve":"stepped"},{"time":1.3333,"x":0,"y":0,"curve":"stepped"},{"time":2.6666,"x":0,"y":0}]},"smile":{"rotate":[{"time":0,"angle":0,"curve":"stepped"},{"time":1.3333,"angle":0,"curve":"stepped"},{"time":2.6666,"angle":0}],"translate":[{"time":0,"x":0,"y":0,"curve":"stepped"},{"time":1.3333,"x":0,"y":0,"curve":"stepped"},{"time":2.6666,"x":0,"y":0}]},"l_hand":{"rotate":[{"time":0,"angle":0,"curve":"stepped"},{"time":1.3333,"angle":0,"curve":"stepped"},{"time":2.6666,"angle":0}],"translate":[{"time":0,"x":0,"y":0,"curve":"stepped"},{"time":1.3333,"x":0,"y":0,"curve":"stepped"},{"time":2.6666,"x":0,"y":0}]},"r_hand":{"rotate":[{"time":0,"angle":0,"curve":"stepped"},{"time":1.3333,"angle":0,"curve":"stepped"},{"time":2.6666,"angle":0}],"translate":[{"time":0,"x":0,"y":0,"curve":"stepped"},{"time":1.3333,"x":0,"y":0,"curve":"stepped"},{"time":2.6666,"x":0,"y":0}]}}},"talk":{"bones":{"body":{"rotate":[{"time":0,"angle":0,"curve":"stepped"},{"time":1,"angle":0}]},"head":{"rotate":[{"time":0,"angle":0,"curve":"stepped"},{"time":1,"angle":0},{"time":1.1666,"angle":-8.59},{"time":1.3333,"angle":0},{"time":1.5,"angle":-8.59},{"time":1.6666,"angle":0,"curve":"stepped"},{"time":2.6666,"angle":0}]},"l_leg":{"rotate":[{"time":0,"angle":0,"curve":"stepped"},{"time":1,"angle":0}]},"l_shoulder":{"rotate":[{"time":0,"angle":-83.81,"curve":"stepped"},{"time":1,"angle":-83.81}]},"r_leg":{"rotate":[{"time":0,"angle":0,"curve":"stepped"},{"time":1,"angle":0}]},"r_shoulder":{"rotate":[{"time":0,"angle":88.34,"curve":"stepped"},{"time":1,"angle":88.34}]},"l_arm":{"rotate":[{"time":0,"angle":0,"curve":"stepped"},{"time":1,"angle":0}]},"l_foot":{"rotate":[{"time":0,"angle":0,"curve":"stepped"},{"time":1,"angle":0}]},"r_arm":{"rotate":[{"time":0,"angle":24.72,"curve":"stepped"},{"time":1,"angle":24.72}]},"r_foot":{"rotate":[{"time":0,"angle":0,"curve":"stepped"},{"time":1,"angle":0}]},"smile":{"rotate":[{"time":0,"angle":0,"curve":"stepped"},{"time":1,"angle":0}]},"l_hand":{"rotate":[{"time":0,"angle":0,"curve":"stepped"},{"time":1,"angle":0}]},"r_hand":{"rotate":[{"time":0,"angle":0,"curve":"stepped"},{"time":1,"angle":0}]}}},"walk":{"bones":{"body":{"rotate":[{"time":0,"angle":0},{"time":0.3333,"angle":-11.8},{"time":0.6666,"angle":0},{"time":1,"angle":-11.8},{"time":1.3333,"angle":0}],"translate":[{"time":0,"x":-2.74,"y":-2.46},{"time":0.3333,"x":2.39,"y":-20.47},{"time":0.6666,"x":-2.74,"y":-2.46},{"time":1,"x":2.39,"y":-20.47},{"time":1.3333,"x":-2.74,"y":-2.46}]},"head":{"rotate":[{"time":0,"angle":0},{"time":0.3333,"angle":-17.7},{"time":0.6666,"angle":0},{"time":1,"angle":-21.33},{"time":1.3333,"angle":0}],"translate":[{"time":0,"x":0,"y":0,"curve":"stepped"},{"time":0.3333,"x":0,"y":0,"curve":"stepped"},{"time":0.6666,"x":0,"y":0,"curve":"stepped"},{"time":1,"x":0,"y":0,"curve":"stepped"},{"time":1.3333,"x":0,"y":0}]},"l_leg":{"rotate":[{"time":0,"angle":4.91},{"time":0.3333,"angle":48.27},{"time":0.6666,"angle":345.2},{"time":1,"angle":311.96},{"time":1.3333,"angle":4.91}],"translate":[{"time":0,"x":6.43,"y":2.96},{"time":0.3333,"x":0,"y":0},{"time":0.6666,"x":-0.03,"y":-1.05},{"time":1,"x":-1.04,"y":36.58},{"time":1.3333,"x":6.43,"y":2.96}]},"l_shoulder":{"rotate":[{"time":0,"angle":-90.31},{"time":0.3333,"angle":-149.66},{"time":0.6666,"angle":-90.31},{"time":1,"angle":-30.95},{"time":1.3333,"angle":-90.31}],"translate":[{"time":0,"x":-0.33,"y":-10.63},{"time":0.3333,"x":0,"y":0},{"time":0.6666,"x":-0.33,"y":-10.63},{"time":1,"x":-0.67,"y":-21.26},{"time":1.3333,"x":-0.33,"y":-10.63}]},"r_leg":{"rotate":[{"time":0,"angle":-0.15},{"time":0.3333,"angle":313.51},{"time":0.6666,"angle":8.58},{"time":1,"angle":39.5},{"time":1.3333,"angle":-0.15}],"translate":[{"time":0,"x":-0.13,"y":-4.22},{"time":0.3333,"x":0,"y":0},{"time":0.6666,"x":8.45,"y":-0.26},{"time":1,"x":-3.09,"y":-16.62},{"time":1.3333,"x":-0.13,"y":-4.22}]},"r_shoulder":{"rotate":[{"time":0,"angle":89.92},{"time":0.3333,"angle":154.37},{"time":0.6666,"angle":89.92},{"time":1,"angle":25.46},{"time":1.3333,"angle":89.92}],"translate":[{"time":0,"x":0,"y":0,"curve":"stepped"},{"time":0.3333,"x":0,"y":0,"curve":"stepped"},{"time":0.6666,"x":0,"y":0,"curve":"stepped"},{"time":1,"x":0,"y":0,"curve":"stepped"},{"time":1.3333,"x":0,"y":0}]},"l_arm":{"rotate":[{"time":0,"angle":-7.22},{"time":0.3333,"angle":-41.05},{"time":0.6666,"angle":-7.22},{"time":1,"angle":26.6},{"time":1.3333,"angle":-7.22}],"translate":[{"time":0,"x":0,"y":0,"curve":"stepped"},{"time":0.3333,"x":0,"y":0,"curve":"stepped"},{"time":0.6666,"x":0,"y":0,"curve":"stepped"},{"time":1,"x":0,"y":0,"curve":"stepped"},{"time":1.3333,"x":0,"y":0}]},"l_foot":{"rotate":[{"time":0,"angle":10.95},{"time":0.3333,"angle":-35.26},{"time":0.6666,"angle":9.09},{"time":1,"angle":-25.89},{"time":1.3333,"angle":10.95}],"translate":[{"time":0,"x":0,"y":0,"curve":"stepped"},{"time":0.3333,"x":0,"y":0,"curve":"stepped"},{"time":0.6666,"x":0,"y":0},{"time":1,"x":2.88,"y":11.97},{"time":1.3333,"x":0,"y":0}]},"r_arm":{"rotate":[{"time":0,"angle":1.08},{"time":0.3333,"angle":34.75},{"time":0.6666,"angle":1.08},{"time":1,"angle":-32.57},{"time":1.3333,"angle":1.08}],"translate":[{"time":0,"x":0,"y":0,"curve":"stepped"},{"time":0.3333,"x":0,"y":0,"curve":"stepped"},{"time":0.6666,"x":0,"y":0,"curve":"stepped"},{"time":1,"x":0,"y":0,"curve":"stepped"},{"time":1.3333,"x":0,"y":0}]},"r_foot":{"rotate":[{"time":0,"angle":0.16},{"time":0.3333,"angle":-25.4},{"time":0.6666,"angle":6.4},{"time":1,"angle":-27.85},{"time":1.3333,"angle":0.16}],"translate":[{"time":0,"x":0,"y":0},{"time":0.3333,"x":-0.63,"y":12.71},{"time":0.6666,"x":0,"y":0,"curve":"stepped"},{"time":1,"x":0,"y":0,"curve":"stepped"},{"time":1.3333,"x":0,"y":0}]},"smile":{"rotate":[{"time":0,"angle":0,"curve":"stepped"},{"time":0.3333,"angle":0,"curve":"stepped"},{"time":0.6666,"angle":0,"curve":"stepped"},{"time":1,"angle":0,"curve":"stepped"},{"time":1.3333,"angle":0}],"translate":[{"time":0,"x":0,"y":0,"curve":"stepped"},{"time":0.3333,"x":0,"y":0,"curve":"stepped"},{"time":0.6666,"x":0,"y":0,"curve":"stepped"},{"time":1,"x":0,"y":0,"curve":"stepped"},{"time":1.3333,"x":0,"y":0}]},"l_hand":{"rotate":[{"time":0,"angle":-4.03},{"time":0.3333,"angle":-24.63},{"time":0.6666,"angle":-4.03},{"time":1,"angle":16.56},{"time":1.3333,"angle":-4.03}],"translate":[{"time":0,"x":0,"y":0,"curve":"stepped"},{"time":0.3333,"x":0,"y":0,"curve":"stepped"},{"time":0.6666,"x":0,"y":0,"curve":"stepped"},{"time":1,"x":0,"y":0,"curve":"stepped"},{"time":1.3333,"x":0,"y":0}]},"r_hand":{"rotate":[{"time":0,"angle":-0.99},{"time":0.3333,"angle":19.32},{"time":0.6666,"angle":-0.99},{"time":1,"angle":-21.3},{"time":1.3333,"angle":-0.99}],"translate":[{"time":0,"x":0,"y":0,"curve":"stepped"},{"time":0.3333,"x":0,"y":0,"curve":"stepped"},{"time":0.6666,"x":0,"y":0,"curve":"stepped"},{"time":1,"x":0,"y":0,"curve":"stepped"},{"time":1.3333,"x":0,"y":0}]},"root":{"rotate":[{"time":0,"angle":0,"curve":"stepped"},{"time":0.3333,"angle":0,"curve":"stepped"},{"time":0.6666,"angle":0,"curve":"stepped"},{"time":1,"angle":0,"curve":"stepped"},{"time":1.3333,"angle":0}],"translate":[{"time":0,"x":0,"y":0,"curve":"stepped"},{"time":0.3333,"x":0,"y":0,"curve":"stepped"},{"time":0.6666,"x":0,"y":0,"curve":"stepped"},{"time":1,"x":0,"y":0,"curve":"stepped"},{"time":1.3333,"x":0,"y":0}]}}}}}